main_packg/__init__.py
main_packg/main.py
try_pub_pypi-0.0.3.dist-info/LICENSE
try_pub_pypi-0.0.3.dist-info/METADATA
try_pub_pypi-0.0.3.dist-info/WHEEL
try_pub_pypi-0.0.3.dist-info/entry_points.txt
try_pub_pypi-0.0.3.dist-info/top_level.txt
try_pub_pypi-0.0.3.dist-info/RECORD
