Metadata-Version: 2.1
Name: try_pub_pypi
Version: 0.0.3
Summary: A small example package
Home-page: https://github.com/seralekseenko/try_pub_pypi
Author: seroleksiienko
Author-email: seroleksiienko@gmail.com
Classifier: Programming Language :: Python :: 3
Classifier: License :: OSI Approved :: GNU General Public License v3 (GPLv3)
Classifier: Operating System :: OS Independent
Requires-Python: >=3.6
License-File: LICENSE
Requires-Dist: numpy ==1.26.4
